modoptima/MasterInferencer.py
modoptima/MasterTrainer.py
modoptima/___init__.py
modoptima/Train/__init__.py
modoptima/Train/yolov7tiny/Trainer.py
modoptima/Train/yolov7tiny/__init__.py
modoptima/Train/yolov7tiny/detect.py
modoptima/Train/yolov7tiny/hubconf.py
modoptima/Train/yolov7tiny/tester.py
modoptima/Train/yolov7tiny/data/__init__.py
modoptima/Train/yolov7tiny/data/coco.yaml
modoptima/Train/yolov7tiny/data/hyp.scratch.custom.yaml
modoptima/Train/yolov7tiny/data/hyp.scratch.p5.yaml
modoptima/Train/yolov7tiny/data/hyp.scratch.p6.yaml
modoptima/Train/yolov7tiny/data/hyp.scratch.tiny.yaml
modoptima/Train/yolov7tiny/data/r50-csp.yaml
modoptima/Train/yolov7tiny/data/x50-csp.yaml
modoptima/Train/yolov7tiny/data/yolor-csp-x.yaml
modoptima/Train/yolov7tiny/data/yolor-csp.yaml
modoptima/Train/yolov7tiny/data/yolor-d6.yaml
modoptima/Train/yolov7tiny/data/yolor-e6.yaml
modoptima/Train/yolov7tiny/data/yolor-p6.yaml
modoptima/Train/yolov7tiny/data/yolor-w6.yaml
modoptima/Train/yolov7tiny/data/yolov3-spp.yaml
modoptima/Train/yolov7tiny/data/yolov3.yaml
modoptima/Train/yolov7tiny/data/yolov4-csp.yaml
modoptima/Train/yolov7tiny/data/yolov7-d6.yaml
modoptima/Train/yolov7tiny/data/yolov7-e6.yaml
modoptima/Train/yolov7tiny/data/yolov7-e6e.yaml
modoptima/Train/yolov7tiny/data/yolov7-tiny.yaml
modoptima/Train/yolov7tiny/data/yolov7-w6.yaml
modoptima/Train/yolov7tiny/data/yolov7.yaml
modoptima/Train/yolov7tiny/data/yolov7_tiny_pruned_quantized_recipe.md
modoptima/Train/yolov7tiny/data/yolov7_tiny_pruned_quantized_recipe_base.md
modoptima/Train/yolov7tiny/data/yolov7_tiny_pruned_ver2.md
modoptima/Train/yolov7tiny/data/yolov7_tiny_pruned_ver2_base.md
modoptima/Train/yolov7tiny/data/yolov7_tiny_pruned_ver2_quantized.md
modoptima/Train/yolov7tiny/data/yolov7x.yaml
modoptima/Train/yolov7tiny/models/__init__.py
modoptima/Train/yolov7tiny/models/common.py
modoptima/Train/yolov7tiny/models/experimental.py
modoptima/Train/yolov7tiny/models/yolo.py
modoptima/Train/yolov7tiny/utils/__init__.py
modoptima-0.0.0.dist-info/METADATA
modoptima-0.0.0.dist-info/WHEEL
modoptima-0.0.0.dist-info/top_level.txt
modoptima-0.0.0.dist-info/RECORD
