Metadata-Version: 2.1
Name: modoptima
Version: 0.0.0
Summary: ModOptima is a library that democratize deep learning model optimizations to developers. Letting them optimize their models with few lines of code.
Home-page: https://github.com/VikasOjha666/modoptima
Author: Vikas Kumar Ojha
Author-email: vikas.ojha894@gmail.com
License: UNKNOWN
Platform: UNKNOWN
Classifier: Programming Language :: Python
Classifier: Programming Language :: Python :: 3.6
Classifier: Programming Language :: Python :: 3.7
Classifier: Programming Language :: Python :: 3.8
Classifier: Programming Language :: Python :: 3.9
Requires-Dist: sparseml
Requires-Dist: numpy
Requires-Dist: opencv-python
Requires-Dist: onnx
Requires-Dist: onnxruntime
Requires-Dist: tqdm
